{
	"configurations" : 
	[
		{
			"directories" : 
			[
				{
					"build" : ".",
					"hasInstallRule" : true,
					"minimumCMakeVersion" : 
					{
						"string" : "3.5"
					},
					"projectIndex" : 0,
					"source" : ".",
					"targetIndexes" : 
					[
						0,
						1,
						2
					]
				}
			],
			"name" : "",
			"projects" : 
			[
				{
					"directoryIndexes" : 
					[
						0
					],
					"name" : "ld08_driver",
					"targetIndexes" : 
					[
						0,
						1,
						2
					]
				}
			],
			"targets" : 
			[
				{
					"directoryIndex" : 0,
					"id" : "ld08_driver::@6890427a1f51a3e7e1df",
					"jsonFile" : "target-ld08_driver-f7a204c3039ed6abeaf7.json",
					"name" : "ld08_driver",
					"projectIndex" : 0
				},
				{
					"directoryIndex" : 0,
					"id" : "ld08_driver_uninstall::@6890427a1f51a3e7e1df",
					"jsonFile" : "target-ld08_driver_uninstall-ca95ab5c3b5073196a29.json",
					"name" : "ld08_driver_uninstall",
					"projectIndex" : 0
				},
				{
					"directoryIndex" : 0,
					"id" : "uninstall::@6890427a1f51a3e7e1df",
					"jsonFile" : "target-uninstall-cec231429f866b2cd4b4.json",
					"name" : "uninstall",
					"projectIndex" : 0
				}
			]
		}
	],
	"kind" : "codemodel",
	"paths" : 
	{
		"build" : "/home/iclab/autorace/build/ld08_driver",
		"source" : "/home/iclab/autorace/src/ld08_driver"
	},
	"version" : 
	{
		"major" : 2,
		"minor" : 0
	}
}
